{
    "version": "13",
    "character_list": {
        "ALEX": "アレックス",
        "BANJOKAZOOIE": "バンジョー＆カズーイ",
        "BAYONETTA": "ベヨネッタ",
        "BLACKPIT": "ブラックピット",
        "BYLETH": "ベレト/ベレス",
        "CAPTAINFALCON": "キャプテンファルコン",
        "CHROM": "クロム",
        "CLOUD": "クラウド",
        "DAISY": "デイジー",
        "DARKSAMUS": "ダークサムス",
        "DEDEDE": "デデデ",
        "DIDDYKONG": "ディディーコング",
        "DONKEYKONG": "ドンキーコング",
        "DRMARIO": "ドクターマリオ",
        "DUCKHUNT": "ダックハント",
        "ENDERMAN": "エンダーマン",
        "FALCO": "ファルコ",
        "FOX": "フォックス",
        "GANONDORF": "ガノンドロフ",
        "GAOGAEN": "ガオガエン",
        "GEKKOUGA": "ゲッコウガ",
        "HERO": "勇者",
        "HIKARI": "ヒカリ",
        "HOMURA": "ホムラ",
        "ICECLIMBER": "アイスクライマー",
        "IGGY": "イギー",
        "IKE": "アイク",
        "INKLING": "インクリング",
        "JOKER": "ジョーカー",
        "KAMUI": "カムイ",
        "KAZUYA": "カズヤ",
        "KEN": "ケン",
        "KINGKROOL": "キングクルール",
        "KIRBY": "カービィ",
        "KOOPA": "クッパ",
        "KOOPAJR": "クッパJr",
        "LARRY": "ラリー",
        "LEMMY": "レミー",
        "LINK": "リンク",
        "LITTLEMAC": "リトルマック",
        "LUCARIO": "ルカリオ",
        "LUCAS": "リュカ",
        "LUCINA": "ルキナ",
        "LUDWIG": "ルドウィッグ",
        "LUIGI": "ルイージ",
        "MARIO": "マリオ",
        "MARTH": "マルス",
        "METAKNIGHT": "メタナイト",
        "MEWTWO": "ミュウツー",
        "MIIBRAWLER": "Miiブラウラー",
        "MIIGUNNER": "Miiガンナー",
        "MIISWORDFIGHTER": "Miiソードファイター",
        "MINMIN": "ミェンミェン",
        "MORTON": "モートン",
        "MRGAMEWATCH": "Mr.ゲーム&ウォッチ",
        "MURABITO": "むらびと",
        "NESS": "ネス",
        "OLIMAR": "ピクミンオリマー",
        "PACKUNFLOWER": "パックンフラワー",
        "PACMAN": "パックマン",
        "PALUTENA": "パルテナ",
        "PEACH": "ピーチ",
        "PICHU": "ピチュー",
        "PIKACHU": "ピカチュウ",
        "PIKMINALPH": "ピクミン&アルフ",
        "PIKMINOLIMAR": "ピクミン&オリマー",
        "PIT": "ピット",
        "POKEMONTRAINER": "ポケモントレーナー",
        "PURIN": "プリン",
        "REFLET": "ルフレ",
        "RICHTER": "リヒター",
        "RIDLEY": "リドリー",
        "ROBOT": "ロボット",
        "ROCKMAN": "ロックマン",
        "ROSETTACHIKO": "ロゼッタチコ",
        "ROY": "ロイ",
        "ROY(KOOPAJR)": "ロイ",
        "RYU": "リュウ",
        "SAMUS": "サムス",
        "SEPHIROTH": "セフィロス",
        "SHEIK": "シーク",
        "SHIZUE": "しずえ",
        "SHULK": "シュルク",
        "SIMON": "シモン",
        "SNAKE": "スネーク",
        "SONIC": "ソニック",
        "SORA": "ソラ",
        "STEVE": "スティーブ",
        "TERRY": "テリー",
        "TOONLINK": "トゥーンリンク",
        "WARIO": "ワリオ",
        "WENDY": "ウェンディ",
        "WIIFITTRAINER": "WiiFitトレーナー",
        "WOLF": "ウルフ",
        "YOSHI": "ヨッシー",
        "YOUNGLINK": "こどもリンク",
        "ZELDA": "ゼルダ",
        "ZEROSUITSAMUS": "ゼロスーツサムス",
        "ZOMBIE": "ゾンビ"
    },
    "icon_list": {
        "ALEX": "chara_2_pickel_01.png",
        "BANJOKAZOOIE": "chara_2_buddy_00.png",
        "BAYONETTA": "chara_2_bayonetta_00.png",
        "BLACKPIT": "chara_2_pitb_00.png",
        "BYLETH": "chara_2_master_01.png",
        "CAPTAINFALCON": "chara_2_captain_00.png",
        "CHROM": "chara_2_chrom_00.png",
        "CLOUD": "chara_2_cloud_00.png",
        "DAISY": "chara_2_daisy_00.png",
        "DARKSAMUS": "chara_2_samusd_00.png",
        "DEDEDE": "chara_2_dedede_00.png",
        "DIDDYKONG": "chara_2_diddy_00.png",
        "DONKEYKONG": "chara_2_donkey_00.png",
        "DRMARIO": "chara_2_mariod_00.png",
        "DUCKHUNT": "chara_2_duckhunt_00.png",
        "ENDERMAN": "chara_2_pickel_07.png",
        "FALCO": "chara_2_falco_00.png",
        "FOX": "chara_2_fox_00.png",
        "GANONDORF": "chara_2_ganon_00.png",
        "GAOGAEN": "chara_2_gaogaen_00.png",
        "GEKKOUGA": "chara_2_gekkouga_00.png",
        "HERO": "chara_2_brave_00.png",
        "HIKARI": "chara_2_elight_00.png",
        "HOMURA": "chara_2_eflame_00.png",
        "ICECLIMBER": "chara_2_ice_climber_00.png",
        "IGGY": "chara_2_koopajr_04.png",
        "IKE": "chara_2_ike_00.png",
        "INKLING": "chara_2_inkling_00.png",
        "JOKER": "chara_2_jack_00.png",
        "KAMUI": "chara_2_kamui_00.png",
        "KAZUYA": "chara_2_demon_00.png",
        "KEN": "chara_2_ken_00.png",
        "KINGKROOL": "chara_2_krool_00.png",
        "KIRBY": "chara_2_kirby_00.png",
        "KOOPA": "chara_2_koopa_00.png",
        "KOOPAJR": "chara_2_koopajr_00.png",
        "LARRY": "chara_2_koopajr_01.png",
        "LEMMY": "chara_2_koopajr_06.png",
        "LINK": "chara_2_link_00.png",
        "LITTLEMAC": "chara_2_littlemac_00.png",
        "LUCARIO": "chara_2_lucario_00.png",
        "LUCAS": "chara_2_lucas_00.png",
        "LUCINA": "chara_2_lucina_00.png",
        "LUDWIG": "chara_2_koopajr_07.png",
        "LUIGI": "chara_2_luigi_00.png",
        "MARIO": "chara_2_mario_00.png",
        "MARTH": "chara_2_marth_00.png",
        "METAKNIGHT": "chara_2_metaknight_00.png",
        "MEWTWO": "chara_2_mewtwo_00.png",
        "MIIBRAWLER": "chara_2_miifighter_00.png",
        "MIIGUNNER": "chara_2_miigunner_00.png",
        "MIISWORDFIGHTER": "chara_2_miiswordsman_00.png",
        "MINMIN": "chara_2_tantan_00.png",
        "MORTON": "chara_2_koopajr_05.png",
        "MRGAMEWATCH": "chara_2_gamewatch_00.png",
        "MURABITO": "chara_2_murabito_00.png",
        "NESS": "chara_2_ness_00.png",
        "OLIMAR": "chara_2_pikmin_00.png",
        "PACKUNFLOWER": "chara_2_packun_00.png",
        "PACMAN": "chara_2_pacman_00.png",
        "PALUTENA": "chara_2_palutena_00.png",
        "PEACH": "chara_2_peach_00.png",
        "PICHU": "chara_2_pichu_00.png",
        "PIKACHU": "chara_2_pikachu_00.png",
        "PIKMINALPH": "chara_2_pikmin_04.png",
        "PIKMINOLIMAR": "chara_2_pikmin_00.png",
        "PIT": "chara_2_pit_00.png",
        "POKEMONTRAINER": "chara_2_ptrainer_00.png",
        "PURIN": "chara_2_purin_00.png",
        "REFLET": "chara_2_reflet_00.png",
        "RICHTER": "chara_2_richter_00.png",
        "RIDLEY": "chara_2_ridley_00.png",
        "ROBOT": "chara_2_robot_00.png",
        "ROCKMAN": "chara_2_rockman_00.png",
        "ROSETTACHIKO": "chara_2_rosetta_00.png",
        "ROY": "chara_2_roy_00.png",
        "ROY(KOOPAJR)": "chara_2_koopajr_02.png",
        "RYU": "chara_2_ryu_00.png",
        "SAMUS": "chara_2_samus_00.png",
        "SEPHIROTH": "chara_2_edge_00.png",
        "SHEIK": "chara_2_sheik_00.png",
        "SHIZUE": "chara_2_shizue_00.png",
        "SHULK": "chara_2_shulk_00.png",
        "SIMON": "chara_2_simon_00.png",
        "SNAKE": "chara_2_snake_00.png",
        "SONIC": "chara_2_sonic_00.png",
        "SORA": "chara_2_sora_00.png",
        "STEVE": "chara_2_pickel_00.png",
        "TERRY": "chara_2_dolly_00.png",
        "TOONLINK": "chara_2_toonlink_00.png",
        "WARIO": "chara_2_wario_00.png",
        "WENDY": "chara_2_koopajr_03.png",
        "WIIFITTRAINER": "chara_2_wiifit_00.png",
        "WOLF": "chara_2_wolf_00.png",
        "YOSHI": "chara_2_yoshi_00.png",
        "YOUNGLINK": "chara_2_younglink_00.png",
        "ZELDA": "chara_2_zelda_00.png",
        "ZEROSUITSAMUS": "chara_2_szerosuit_00.png",
        "ZOMBIE": "chara_2_pickel_06.png"
    },
    "i18n_convert_list": {},
    "bgm_list": {
        "命の灯火": false,
        "Lifelight": false,
        "メニュー": false,
        "戦場": false,
        "終点": false,
        "組み手": false,
        "勝ち上がり乱闘：壁画": false,
        "勝ち上がり乱闘：敗北": false,
        "勝ちあがり乱闘：最終結果": false,
        "勝ち上がり乱闘：ボーナスステージ": false,
        "マスターハンド": false,
        "クレイジーハンド": false,
        "マスターハンド・クレイジーハンド": false,
        "光の世界：序章": false,
        "光の世界：進軍": false,
        "光の世界：基地": false,
        "闇の世界": false,
        "闇の世界：謎の空間": false,
        "最終決戦": false,
        "最終決戦：変化後": false,
        "キーラ": false,
        "ダーズ": false,
        "キーラ・ダーズ": false,
        "メインテーマピアノソロ": false,
        "スピリッツ：ルーレット": false,
        "スピリッツ：手もち": false,
        "スピリッツ：名鑑／アイテム": false,
        "トーナメント：対戦表": false,
        "トーナメント：優勝発表": false,
        "トレーニング": false,
        "コレクション": false,
        "ショップ": false,
        "模擬戦": false,
        "大観戦": false,
        "スマブラDX：オープニング": false,
        "スマブラDX：オープニング[X]": false,
        "スマブラX：メインテーマ": false,
        "スマブラ：How to play": false,
        "スマブラDX：How to play": false,
        "スマブラ：メニュー": false,
        "スマブラDX：メニュー": false,
        "スマブラDX：メニュー[X]": false,
        "スマブラDX：メニュー2": false,
        "ボスバトル(スマブラX)": false,
        "スマブラX：メニュー": false,
        "スマブラfor：メニュー": false,
        "キャラクターセレクト(スマブラ)": false,
        "対戦結果[for]": false,
        "戦場(スマブラDX)": false,
        "戦場(スマブラDX)[for]": false,
        "戦場(スマブラX)": false,
        "戦場Ver.2(スマブラX)": false,
        "戦場(スマブラfor)": false,
        "終点(スマブラ)": false,
        "終点(スマブラDX)": false,
        "ギガクッパ": false,
        "終点(スマブラX)": false,
        "終点(スマブラfor)": false,
        "終点Ver.2(スマブラfor)": false,
        "組み手(スマブラfor)": false,
        "百人組み手": false,
        "百人組み手2": false,
        "情け無用組み手": false,
        "スマブラ：スタッフロール": false,
        "スマブラ：スタッフロール[X]": false,
        "スマブラ：スタッフロール[for]": false,
        "スマブラX：スタッフロール": false,
        "スマブラfor：スタッフロール": false,
        "ボーナスゲーム(スマブラ)": false,
        "メタ・クリスタル": false,
        "デュエルゾーン": false,
        "トレーニングモード": false,
        "ターゲットをこわせ！(スマブラDX)": false,
        "メタルバトル": false,
        "フィギュア名鑑(スマブラDX)": false,
        "トーナメント1(スマブラDX)": false,
        "トーナメント2(スマブラDX)": false,
        "オールスター休憩所(スマブラDX)": false,
        "ターゲットをこわせ！(スマブラX)": false,
        "アドベンチャーマップ(スマブラX)": false,
        "ステップ：平地(スマブラX)": false,
        "ステップ：亜空間(スマブラX)": false,
        "ステップ：亜空間Ver.3(スマブラX)": false,
        "ボス戦闘曲1(スマブラX)": false,
        "ボス戦闘曲2(スマブラX)": false,
        "ホームランコンテスト": false,
        "フィギュア名鑑(スマブラX)": false,
        "シール名鑑/アルバム/ゲーム年表(スマブラX)": false,
        "コインシューター": false,
        "ステージ作り(スマブラX)": false,
        "トーナメント登録(スマブラX)": false,
        "トーナメント表(スマブラX)": false,
        "トーナメント試合終了(スマブラX)": false,
        "オールスター休憩所(スマブラX)": false,
        "オンライン練習ステージ(スマブラX)": false,
        "シンプル：結果(スマブラfor)": false,
        "シンプル：最終結果(スマブラfor)": false,
        "シンプル：失敗(スマブラfor)": false,
        "マスターハンド(スマブラfor)": false,
        "マスターコア": false,
        "マスターフォレスト：第1次攻撃": false,
        "マスターフォレスト：第2次攻撃": false,
        "マスターサイド：ステージセレクト": false,
        "フィギュアラッシュ": false,
        "フィギュアショップ": false,
        "フィギュア名鑑/フィギュアディスプレイ(スマブラfor)": false,
        "リプレイ/アルバム/戦いの記録(スマブラfor)": false,
        "オールスター休憩所(スマブラfor)": false,
        "オンライン練習ステージ(スマブラfor)": false,
        "すれちがい大乱闘": false,
        "イベント戦(スマブラfor)": false,
        "ワールドスマッシュ：マップ": false,
        "": false,
        "地上BGM(スーパーマリオブラザーズ)": false,
        "地上BGM(スーパーマリオブラザーズ)[64]": false,
        "地上BGM(スーパーマリオブラザーズ)[DX]": false,
        "地上BGM(スーパーマリオブラザーズ)[X]": false,
        "バンド演奏地上BGM(スーパーマリオブラザーズ)": false,
        "地上BGM/地下BGM(スーパーマリオブラザーズ)": false,
        "地下BGM(スーパーマリオブラザーズ)": false,
        "水中BGM(スーパーマリオブラザーズ)": false,
        "スーパーマリオブラザーズメドレー": false,
        "スーパーマリオブラザーズ2メドレー": false,
        "地上BGM(スーパーマリオUSA)": false,
        "ローリングヒルズA": false,
        "ボスBGM(スーパーマリオUSA)": false,
        "地上BGM(スーパーマリオブラザーズ3)[DX]": false,
        "地上BGM(スーパーマリオブラザーズ3)": false,
        "スーパーマリオブラザーズ3メドレー": false,
        "砦のボス(スーパーマリオブラザーズ3)": false,
        "飛行船BGM(スーパーマリオブラザーズ3)": false,
        "魔王クッパ": false,
        "地下BGM(スーパーマリオランド)": false,
        "スーパーマリオワールド：タイトル/エンディング": false,
        "地上BGM(スーパーマリオワールド)": false,
        "スーパーマリオワールドメドレー": false,
        "お城BGM/砦のボス(マリオワールド/マリオ3)": false,
        "砦ボス戦(スーパーマリオワールド)": false,
        "スーパーマリオ64：メインテーマ": false,
        "スライダー": false,
        "ドルピックタウン": false,
        "リコハーバー": false,
        "Newスーパーマリオブラザーズ：メインテーマ": false,
        "Super Mario Galaxy": false,
        "エッグプラネット": false,
        "天文台のロゼッタ/チコのテーマ": false,
        "ウィンドガーデン": false,
        "チャンピオンシップロード": false,
        "Theme of SMG2": false,
        "星船はゆく": false,
        "空島": false,
        "マグマモンスター": false,
        "新銀河帝国": false,
        "宿命の決戦": false,
        "地上BGM/水中BGM(スーパーマリオ3Dランド)": false,
        "アスレチック(Newスーパーマリオブラザーズ2)": false,
        "地上BGM(Newスーパーマリオブラザーズ2)": false,
        "地上BGM(NewスーパーマリオブラザーズU)": false,
        "スーパーベルの丘": false,
        "スーパータワーの決戦2": false,
        "スーパーマリオメーカー：タイトル": false,
        "ダイナフォー": false,
        "ニュードンク・シティ": false,
        "Jump Up,Super Star!": false,
        "スチームガーデン": false,
        "月の地下洞くつ": false,
        "Break Free(Lead the Way)": false,
        "ザラザラ砂漠": false,
        "ちょいと強い奴らに要注意!?": false,
        "イン・ザ・ファイナル": false,
        "ペーパーマリオメドレー": false,
        "TRY AND TRY!": false,
        "急げば間に合う!": false,
        "トリオで大混戦!!!": false,
        "アタック・エンド・ラン!": false,
        "バトル!(ペーパーマリオカラースプラッシュ)": false,
        "これがボコスカバトル!": false,
        "はちゃめちゃ!": false,
        "マリオパーティアイランドツアー：タイトル": false,
        "ロケットレースギャラクシー": false,
        "マリオテニス/マリオゴルフ": false,
        "ワールドツアー": false,
        "スタジアムのテーマ(マリオテニスウルトラスマッシュ)": false,
        "キングダムスタジアム：夜": false,
        "カントリーフィールド：先攻側": false,
        "マリオテニスエースのテーマ": false,
        "スタジアムのテーマ(マリオテニスエース)": false,
        "ルイージマンション：メインテーマ": false,
        "ルイージマンション：メインテーマ[X]": false,
        "ルイージマンションシリーズメドレー": false,
        "探索-ウラメ～シ屋敷Ver.(instrumental)": false,
        "マリオブラザーズ": false,
        "Fever": false,
        "Chill[X]": false,
        "Chill[for]": false,
        "マリオペイントメドレー": false,
        "旅立ちのひっこ抜き峠": false,
        "火ふき山の主": false,
        "マリオvs.ドンキーコングみんなでミニランド：タイトル": false,
        "": false,
        "マリオサーキット(スーパーマリオカート)": false,
        "ルイージサーキット(マリオカート64)": false,
        "レインボーロード(マリオカートダブルダッシュ!!)": false,
        "ワルイージピンボール(マリオカートDS)": false,
        "キノコキャニオン": false,
        "サーキット(マリオカート7)": false,
        "レインボーロード(マリオカート7)": false,
        "レインボーロード シリーズメドレー": false,
        "マリオカートスタジアム(マリオカート8)": false,
        "マリオサーキット(マリオカート8)": false,
        "スカイガーデン(マリオカート8)": false,
        "レインボーロード(マリオカート8)": false,
        "エキサイトバイク(マリオカート8)": false,
        "ドラゴンロード": false,
        "ツルツルツイスター": false,
        "": false,
        "ドンキーコング：オープニング": false,
        "ドンキーコングリターンズ": false,
        "ドンキーコングリターンズ【ドンキーファミリーボーカル】": false,
        "ドンキーコング": false,
        "25m BGM": false,
        "ドンキーコング/ドンキーコングJR.メドレー": false,
        "THE MAP PAGE/BPNUS LEVEL": false,
        "JUNGLE LEVEL[64]": false,
        "JUNGLE LEVEL[DX]": false,
        "JUNGLE LEVEL[X]": false,
        "JUNGLE LEVEL Jazz Style[for]": false,
        "バナナジャングル": false,
        "ふみふみラビリンス": false,
        "The Ice Cave": false,
        "Funky Kong Page": false,
        "ラトリーに大変身": false,
        "THE PIRATE SHIP": false,
        "KING K.ROOL/SHIP DECK2": false,
        "とげとげタルめいろ": false,
        "けっせん!キャプテンクルール": false,
        "モンキーラップ": false,
        "嵐の丘の戦い": false,
        "ボス2(ドンキーコングジャングルクライマー)": false,
        "モグリャーのこうじげんば": false,
        "スリル!ギアフライト": false,
        "マングローブのいりえ": false,
        "": false,
        "ゼルダの伝説:タイトル": false,
        "地上BGM(ゼルダの伝説)": false,
        "地上BGM(ゼルダの伝説)[64]": false,
        "地上BGM(ゼルダの伝説)[DX]": false,
        "地上BGM(ゼルダの伝説)[X]": false,
        "地上BGM/地下BGM(ゼルダの伝説)[for]": false,
        "ゼルダの伝説メドレー": false,
        "デスマウンテンBGM": false,
        "神殿": false,
        "大神殿/神殿": false,
        "表の地上": false,
        "裏の地上[X]": false,
        "裏の地上[for]": false,
        "裏の山と森": false,
        "タルタル高原": false,
        "時のオカリナメドレー": false,
        "ハイラル平原メインテーマ": false,
        "サリアの歌": false,
        "サリアの歌/中ボス": false,
        "嵐の歌": false,
        "ゲルドの谷": false,
        "タルミナ平原": false,
        "大海原/メニューセレクト": false,
        "竜の島": false,
        "モルド・ゲイラ": false,
        "青の巫女の村": false,
        "ゼルダの伝説トワイライトプリンセス：メインテーマ": false,
        "傷だらけのミドナ": false,
        "忘れられた里": false,
        "汽車フィールド その2": false,
        "女神の詩": false,
        "ロウラルメインテーマ": false,
        "ゼルダの伝説トライフォース3銃士:メインテーマ": false,
        "森林エリア(ゼルダの伝説 トライフォース3銃士)": false,
        "Nintendo Switch Presentation 2017 Trailer BGM": false,
        "ゼルダの伝説ブレスオブザワイルド：メインテーマ": false,
        "カッシーワのテーマ": false,
        "ハイラル城(屋外)": false,
        "厄災ガノン戦−第二形態": false,
        "": false,
        "メトロイド:タイトル": false,
        "ブリンスタ[64]": false,
        "ブリンスタ[DX]": false,
        "ブリンスタ[X]": false,
        "ブリンスタ深部": false,
        "ブリンスタ深部[DX]": false,
        "ノルフェア": false,
        "脱出": false,
        "メトロイド:エンディング": false,
        "vs.リドリー": false,
        "vs.リドリー[X]": false,
        "宇宙戦士サムスアランのテーマ": false,
        "Sector1": false,
        "メトロイドプライム:オープニング/メニュー": false,
        "vs.パラサイトクイーン": false,
        "vs.メタリドリー": false,
        "マルチプレイ(メトロイドプライム2ダークエコーズ)": false,
        "PsychoBits": false,
        "拘束の死闘": false,
        "灼熱の溶岩魚": false,
        "宿敵リドリー": false,
        "メトロイドプライムフェデレーションフォース:メインテーマ": false,
        "SplashScreen": false,
        "Area1～5熱帯(メトロイドサムスリターンズ)": false,
        "ラヴァケイブス(メトロイドサムスリターンズ)": false,
        "BOSS4(メトロイドサムスリターンズ)": false,
        "リザルト(メトロイドサムスリターンズ)": false,
        "": false,
        "アスレチック(スーパーマリオワールド)": false,
        "ヨッシーアイランド[X]": false,
        "ヨッシーアイランド[for]": false,
        "アスレチック(ヨッシーアイランド)": false,
        "ヨッシーのうた[64]": false,
        "ヨッシーのうた[DX]": false,
        "ヨッシーのおはなし": false,
        "おはなばたけ": false,
        "こうやのテーマ": false,
        "ヨッシーNewアイランド:メインテーマ": false,
        "しゃくねつのせかい": false,
        "ヨッシーウールワールド:メインテーマ": false,
        "": false,
        "グリーングリーンズ[DX]": true,
        "グリーングリーンズ[for]": true,
        "星のカービィ原曲メドレー": true,
        "デデデ大王のテーマ[X]": true,
        "デデデ大王のテーマ[for]": true,
        "星のカービィ:STAFFROLL": true,
        "ボスのテーマメドレー(星のカービィシリーズ)": true,
        "アイスクリームアイランド": true,
        "バタービルディング[X]": true,
        "バタービルディング[for]": true,
        "激突!グルメレース": true,
        "激突!グルメレース[64]": true,
        "激突!グルメレース[DX]": true,
        "洞窟大作戦": true,
        "メタナイトの逆襲": true,
        "vs.マルク": true,
        "ポップスター": true,
        "ゼロツー戦": true,
        "森ステージ": true,
        "ヴァレリオン": true,
        "コルダ": true,
        "シティトライアル": true,
        "伝説のエアライドマシン": true,
        "森・自然エリア": true,
        "ドロッチェ団のテーマ": true,
        "ぼうけんのはじまり": true,
        "森をぬけて": true,
        "スカイタワー": true,
        "デンジャラスディナー": true,
        "CROWNED": true,
        "浮遊大陸の花園": true,
        "狂花水月": true,
        "この星をかけた魂の戦い": true,
        "CROWNED:Ver.2": true,
        "キカイのせかいのだいぼうけん": true,
        "桃球発進!ロボボアーマー": true,
        "カービィバトルデラックス!:メインテーマ": true,
        "友ときずなの戦い2": true,
        "": false,
        "スターフォックス：メインテーマ": false,
        "コーネリア(スターフォックス)": false,
        "スペース・アマダ": false,
        "スターフォックス・メドレー": false,
        "スターフォックス64：メインテーマ[64]": false,
        "スターフォックス64：メインテーマ[DX]": false,
        "スターフォックス64：メインテーマ[X]": false,
        "スターウルフ": false,
        "スターウルフ[X]": false,
        "スターウルフ/セクターZ[for]": false,
        "エリア6(スターフォックス64)": false,
        "エリア6Ver.2(スターフォックス64)": false,
        "エリア6/ミサイル撃墜ミッション": false,
        "戦闘宙域": false,
        "氷原突破せよ": false,
        "惑星コーネリア(スターフォックスゼロ)": false,
        "セクターΩ宙域": false,
        "セクター宙域": false,
        "惑星コーネリア再び(スターフォックスゼロ)": false,
        "": false,
        "ポケットモンスター赤・緑:メインテーマ[64]": false,
        "ポケットモンスター赤・緑:メインテーマ[DX]": false,
        "ポケットモンスター赤・緑:メインテーマ[X]": false,
        "トキワの道−マサラより/ニビシティ(ポケットモンスター赤・緑)": false,
        "ポケモンセンター(ポケットモンスター赤・緑)": false,
        "ポケモンジム/進化(ポケットモンスター赤・緑)": false,
        "ポケットモンスター赤・緑メドレー": false,
        "ポケットモンスター金・銀メドレー": false,
        "戦闘!野生ポケモン(ポケットモンスタールビー・サファイア)": false,
        "チャンピオンロード(ポケットモンスタールビー・サファイア)": false,
        "戦闘!野生ポケモン(ポケットモンスターダイヤモンド・パール)": false,
        "戦闘!ギンガ団": false,
        "209ばんどうろ(ポケットモンスターダイヤモンド・パール)": false,
        "戦闘!ディアルガ・パルキア/やりのはしら": false,
        "戦闘!チャンピオン/チャンピオンシロナ": false,
        "10ばんどうろ(ポケットモンスターブラック・ホワイト)": false,
        "Nの城": false,
        "戦闘!ゼクロム・レシラム": false,
        "23ばんどうろ(ポケットモンスターブラック2・ホワイト2)": false,
        "戦闘!野生ポケモン(ポケットモンスターX・Y)": false,
        "戦闘!トレーナー(ポケットモンスターX・Y)": false,
        "戦闘!フレア団": false,
        "ミアレシティ": false,
        "チャンピオンロード(ポケットモンスターX・Y)": false,
        "戦闘!チャンピオン(ポケットモンスターX・Y)": false,
        "決戦！ダイゴ": false,
        "戦闘!伝承者ヒガナ": false,
        "戦闘！野生ポケモン(ポケットモンスターサン・ムーン)": false,
        "戦闘!トレーナー(ポケットモンスターサン・ムーン)": false,
        "戦闘!しまキング・しまクイーン": false,
        "戦闘!グラジオ": false,
        "戦闘!四天王/戦闘!ソルガレオ・ルナアーラ": false,
        "頂上決戦!": false,
        "": false,
        "MUTECITY": false,
        "MUTECITY[DX]": false,
        "MUTECITY[X]": false,
        "MUTECITY[for]": false,
        "BIGBLUE": false,
        "BIGBLUE[DX]": false,
        "SANDOCEAN": false,
        "DEATHWIND": false,
        "F-ZEROメドレー": false,
        "SILENCE": false,
        "PORTTOWN": false,
        "REDCANYON": false,
        "WHITELAND": false,
        "WHITELANDⅡ": false,
        "FIREFIELD": false,
        "CARSELECT": false,
        "DREAMCHASER": false,
        "DEVIL’S CALL IN YOUR HEART": false,
        "CLIMB UP! AND GET THE LAST CHANCE!": false,
        "BRAINCLEANER": false,
        "SHOTGUNKISS": false,
        "PLANETCOLORS": false,
        "": false,
        "Pollyanna(I Believe In You)": false,
        "Humoresque Of A Little Dog": false,
        "マジカント": false,
        "マジカント[for]": false,
        "Bein’Friend": false,
        "SNOWMAN": false,
        "オネットのテーマ/ウインターズのテーマ": false,
        "フォーサイド": false,
        "フォーサイド[DX]": false,
        "スマイルアンドティアーズ": false,
        "MOTHER3愛のテーマ": false,
        "いわれなきリベンジ/ブッコワシ賛歌": false,
        "ユートピアでしょ?!": false,
        "ポーキーのテーマ": false,
        "": false,
        "ファイアーエムブレムのテーマ": false,
        "ファイアーエムブレムのテーマ(Ver.Heroes)": false,
        "Code Name:F.E.": false,
        "Lords-邂逅": false,
        "ストーリー5出会い": false,
        "暗黒竜メドレー": false,
        "闘技場シリーズメドレー": false,
        "解放への勇進": false,
        "ミラの加護とともに(セリカマップ1)": false,
        "戦い1(ファイアーエムブレム外伝)": false,
        "Lords-決戦": false,
        "神に抗う者よ": false,
        "この旗の下に": false,
        "進撃": false,
        "ファイアーエムブレム紋章の謎メドレー": false,
        "出会いのテーマシリーズメドレー": false,
        "失意の果て": false,
        "あの空の向こうに(ロイの旅立ち)": false,
        "Winning Road〜ロイの希望": false,
        "攻撃(烈火の剣)": false,
        "進撃準備": false,
        "Victory is Near": false,
        "Crimea Army Sortie": false,
        "Against The Dark Knight": false,
        "Powerhungry Fool": false,
        "絆永久に": false,
        "忠義尽くさん": false,
        "決起の時": false,
        "序幕〜炎": false,
        "宿命〜炎": false,
        "遠征〜炎": false,
        "「I」〜為": false,
        "if〜ひとり思う〜": false,
        "Lost in Thoughts All Alone": false,
        "if〜ひとり思う〜[for]": false,
        "ギブアップフォー": false,
        "亡国の王者": false,
        "王の子は煉獄に踊る": false,
        "": false,
        "フラットゾーン": false,
        "フラットゾーン2": false,
        "": false,
        "パルテナの鏡:タイトル": false,
        "パルテナの鏡原曲メドレー": false,
        "冥府界": false,
        "地上界": false,
        "ボス戦1(新・光神話パルテナの鏡)": false,
        "マグナのテーマ": false,
        "ブラックピットのテーマ": false,
        "星賊船": false,
        "ハデスのテーマ": false,
        "初期化爆弾の恐怖": false,
        "雷雲の庭園": false,
        "銀河の聖域": false,
        "崩壊エンジェランド": false,
        "": false,
        "メイドインワリオ": false,
        "メイドインワリオメドレー": false,
        "アシュリーのテーマ[X]": false,
        "Ashley’s Song": false,
        "アシュリーのテーマ[for]": false,
        "マイクがスキ☆スキ": false,
        "Mike’s Song": false,
        "こちらモナ☆ピザ": false,
        "Mona Pizza’s Song": false,
        "いせき(ワリオランドシェイク)": false,
        "ゲーマー": false,
        "": false,
        "ピクミン:メインテーマ": false,
        "希望の森": false,
        "ステージクリア/タイトル(ピクミン)": false,
        "環境音": false,
        "ワールドマップ(ピクミン2)": false,
        "ステージセレクト(ピクミン2)": false,
        "再開の花園": false,
        "ミッションモード(ピクミン3)": false,
        "ゆらめく湖のヌシ": false,
        "空を切りさく稲妻": false,
        "雪山を抜けて": false,
        "希望のかけら": false,
        "": false,
        "どうぶつの森:タイトル": false,
        "ゆけ!けけライダー": false,
        "おいでよどうぶつの森:タイトル": false,
        "おいでよどうぶつの森:タイトル[X]": false,
        "午前2時(おいでよどうぶつの森)": false,
        "役場とタヌキ商店(おいでよどうぶつの森)": false,
        "純喫茶”ハトの巣”(おいでよどうぶつの森)": false,
        "街の広場/タイトル(街へいこうよどうぶつの森/おいでよどうぶつの森)": false,
        "フィールド19時(晴)/商店街(とびだせどうぶつの森)": false,
        "かっぺいの歌": false,
        "ツアー(とびだせどうぶつの森)": false,
        "コトブキランドメドレー": false,
        "けけアイドル": false,
        "どうぶつの森ハッピーホームデザイナー:タイトル": false,
        "完成デモ": false,
        "アーバンけけ": false,
        "けけウェスタン": false,
        "ニューオリンズそんぐ": false,
        "けけのロケンロール": false,
        "ユーロビート": false,
        "ペルーのうた": false,
        "": false,
        "WiiFit:メインメニュー": false,
        "燃焼フープダンス": false,
        "リズムボクシング": false,
        "踏み台ダンス": false,
        "ヨガ": false,
        "スケボーフリーモード": false,
        "いたずらモグウェイ": false,
        "WiiFitPlusメドレー": false,
        "トレーニングメニュー(WiiFitU)": false,
        "リュージュ": false,
        "": false,
        "マイナーサーキット": false,
        "ランニング/カウントダウン": false,
        "ワールドサーキット": false,
        "PUNCH-OUT!!(Wii):タイトル": false,
        "": false,
        "敵との対峙": false,
        "戦闘!(ゼノブレイド)": false,
        "ガウル平原": false,
        "ガウル平原/夜": false,
        "ゼノブレイドメドレー": false,
        "行く手を阻む者": false,
        "名を冠する者たち": false,
        "機の律動": false,
        "戦闘!!(ゼノブレイド2)": false,
        "行く手を阻む者たち": false,
        "それでも、前へ進め!": false,
        "": false,
        "Splattack!": false,
        "Ink or Sink": false,
        "Seaskape": false,
        "Kraken Up": false,
        "Metalopod": false,
        "Quick Start": false,
        "Now or Never!": false,
        "Now or Never!(スプラトゥーン)": false,
        "Now or Never!(スプラトゥーン2)": false,
        "キミ色に染めて": false,
        "イマ・ヌラネバー!(スプラトゥーン)": false,
        "イマ・ヌラネバー!(スプラトゥーン2)": false,
        "Octoweaponry": false,
        "I am Octavio": false,
        "シオカラ節": false,
        "トキメキ☆ボムラッシュ": false,
        "Inkoming!": false,
        "Rip Entry": false,
        "Undertow": false,
        "Don’t Slip": false,
        "Endolphin Surge": false,
        "フルスロットル・テンタクル": false,
        "リップル・リフレイン": false,
        "レッド・ホット・エゴイスト": false,
        "囂々": false,
        "": false,
        "THEME OF TARA": false,
        "THEME OF SOLID SNAKE": false,
        "Cavern": false,
        "Encounter": false,
        "Yell”Dead Cell”": false,
        "Snake Eater": false,
        "Snake Eater(Instrumental)": false,
        "Battle In The Base": false,
        "MGS4〜愛のテーマ〜": false,
        "Calling To The Night": false,
        "METAL GEAR SOLID PEACE WALKER MAIN THEME": false,
        "": false,
        "Green Hill Zone": false,
        "Scrap Brain Zone": false,
        "Emerald Hill Zone": false,
        "Sonic Boom": false,
        "Angel Island Zone": false,
        "Super Sonic Racing": false,
        "Open Your Heart": false,
        "Live&amp;Learn": false,
        "Escape Frome The City": false,
        "Sonic Heroes": false,
        "His World(THEME OF SONIC THE HEDGEHOG〜2006 E3 VERSION〜)": false,
        "Seven Ring In Hand": false,
        "Knight Of The Wind": false,
        "Reach For The Stars": false,
        "Rooftop Run": false,
        "Wonder World": false,
        "Windy Hill-Zone1": false,
        "Lights,Camera,Action!-Studiopolis Zone Act1": false,
        "Fist Bump": false,
        "Sunset Heights": false,
        "": false,
        "CUTMAN STAGE": false,
        "GUTSMAN STAGE": false,
        "ICEMAN STAGE": false,
        "BOMBMAN STAGE": false,
        "FIREMAN STAGE": false,
        "ロックマン2メドレー": false,
        "METALMAN STAGE": false,
        "AIRMAN STAGE": false,
        "QUICKMAN STAGE": false,
        "CRASHMAN STAGE": false,
        "FLASHMAN STAGE": false,
        "WOODMAN STAGE": false,
        "HARDMAN STAGE": false,
        "TOPMAN STAGE": false,
        "SNAKEMAN STAGE": false,
        "SPARKMAN STAGE": false,
        "SHADOWMAN STAGE": false,
        "ロックマン4メドレー": false,
        "GRAVITYMAN STAGE": false,
        "NAPALMMAN STAGE": false,
        "DARKMAN STAGE": false,
        "Flash In The Dark(Dr.Wily Stage1)": false,
        "We’re The Robots(Dr.Wily Stage2)": false,
        "ロックマン原曲メドレー": false,
        "ロックマン2原曲メドレー": false,
        "ロックマン3原曲メドレー": false,
        "ロックマン4〜6原曲メドレー": false,
        "OPENING STAGE": false,
        "X vs ZERO": false,
        "ゼロ(Theme of ZERO(frome Rockman X))": false,
        "Shooting Star": false,
        "": false,
        "パックマン": false,
        "パックマン(クラブMIX)": false,
        "PAC-MAN’S PARK/BLOCK TOWN": false,
        "ギャラガメドレー": false,
        "マッピーメドレー": false,
        "リブルラブル原曲メドレー": false,
        "メトロクロス原曲メドレー": false,
        "スカイキッド原曲メドレー": false,
        "エリア1(ドラゴンスピリット)": false,
        "ナムコアーケード’80s原曲メドレー2": false,
        "": false,
        "Ryu Stage": false,
        "Ken Stage": false,
        "Guile stage": false,
        "Balrog Stage": false,
        "Player Select Type A": false,
        "Ryu Stage Type A": false,
        "Ken Stage Type A": false,
        "E.Honda Stage Type A": false,
        "Chun-Li Stage Type A": false,
        "Blanka Stage Type A": false,
        "Zangef Stage Type A": false,
        "Guile Stage Type A": false,
        "Dhalsim Stage Type A": false,
        "M.Bison Stage Type A": false,
        "Balrog Stage Type A": false,
        "Sagat Stage Type A": false,
        "Vega Stage Type A": false,
        "T.Hawk Stage Type A": false,
        "Fei Long Stage Type A": false,
        "Dee Jay Stage Type A": false,
        "Cammy Stage Type A": false,
        "Player Select Type B": false,
        "Ryu Stage Type B": false,
        "Ken Stage Type B": false,
        "E.Honda Stage Type B": false,
        "Chun-Li Stage Type B": false,
        "Blanka Stage Type B": false,
        "Zangief Stage Type B": false,
        "Guile Stage Type B": false,
        "Dhalsim Stage Type B": false,
        "M.Bison Stage Type B": false,
        "Balrog Stage Type B": false,
        "Sagat Stage Type B": false,
        "Vega Stage Type B": false,
        "T.Hawk Stage Type B": false,
        "Fei Long Stage Type B": false,
        "Dee Jay Stage Type B": false,
        "Cammy Stage Type B": false,
        "": false,
        "闘う者達": false,
        "更に闘う者達": false,
        "": false,
        "Theme Of Bayonetta – Mysterious Destiny(instrumental)": false,
        "One Of A Kind": false,
        "Riders Of The Light": false,
        "Let’s Hit The Climax!": false,
        "Red&amp;Black": false,
        "After Burner(∞Climax Mix)": false,
        "友よ": false,
        "Let’s Dance,Boys!": false,
        "Theme Of Bayonetta 2 – Tomorrow Is Mine(instrumental)": false,
        "The Legend Of Aesir": false,
        "Time For The Climax!": false,
        "": false,
        "Vampire Killer": false,
        "Starker/Wicked Child": false,
        "Out of Time": false,
        "Nothing to Lose": false,
        "Black Night": false,
        "Bloody Tears/Monster Dance": false,
        "Dwelling of Doom": false,
        "十字架を胸に": false,
        "夜まで待てない": false,
        "Beginning": false,
        "Mad Forest": false,
        "Aquarius": false,
        "シモン・ベルモンドのテーマ": false,
        "シモン・ベルモンドのテーマ(THE ARCADE)": false,
        "乾坤の血族": false,
        "Slash": false,
        "幻想的舞曲": false,
        "Iron-Blue Intention": false,
        "ドラキュラ城": false,
        "黄金の舞曲": false,
        "失われた彩画": false,
        "悲境の貴公子": false,
        "Awake": false,
        "荒城回廊": false,
        "真実の嘆き": false,
        "漆黒の進攻": false,
        "闇夜の激突": false,
        "斬り裂かれた静寂": false,
        "Hail from the Past": false,
        "Jail of Jewel": false,
        "黄昏の聖痕": false,
        "漆黒の翼": false,
        "行け!月風魔": false,
        "": false,
        "ダックハントメドレー": false,
        "ダックハントメドレー[for]": false,
        "バルーンファイトメドレー": false,
        "バルーントリップ[X]": false,
        "バルーントリップ[for]": false,
        "クルクルランド": false,
        "アイスクライマー[DX]": false,
        "アイスクライマー[X]": false,
        "レッキングクルーメドレー": false,
        "レッキングクルーメドレー[for]": false,
        "レッキングクルー原曲メドレー": false,
        "BGM B:パワーアップ(レッキングクルー)": false,
        "ブロック&amp;ジャイロ": false,
        "マッハライダー": false,
        "ファミコン・メドレー": false,
        "謎の村雨城メドレー": false,
        "道中面(謎の村雨城)": false,
        "新・鬼ヶ島メドレー": false,
        "3Dホットラリー：タイトル": false,
        "テトリスTypeA": false,
        "テトリス TypeB": false,
        "遊遊記メドレー": false,
        "ライトプレーン": false,
        "ライトプレーン[for]": false,
        "ライトプレーン(ボーカルMIX)[for]": false,
        "ジェット機": false,
        "ペダルグラインダー": false,
        "トンネルシーン(X(エックス))": false,
        "トンネルシーン(X-RETURNS)": false,
        "リップのテーマ": false,
        "カルドセプト": false,
        "リボルト—希望への決起-": false,
        "好敵手バトル": false,
        "Golden Forest": false,
        "戦闘シーン/最終ボス戦(黄金の太陽)": false,
        "The Weyard": false,
        "英雄の証〜4Version": false,
        "咆哮/リオレウス": false,
        "ピクトチャット": false,
        "エレクトロプランクトン": false,
        "シャワーBGM": false,
        "シャワーBGM[for]": false,
        "シャワーBGM(ボーカルMIX)[for]": false,
        "脳を鍛える大人のDSトレーニング": false,
        "もっと脳を鍛える大人のDSトレーニング:メニュー": false,
        "やわらかあたま塾:タイトル": false,
        "The Valedictory Elegy": false,
        "しゃべる!DSお料理ナビ": false,
        "マリオネーションギア": false,
        "Wiiショッピングチャンネル": false,
        "似顔絵広場": false,
        "似顔絵チャンネル": false,
        "牛ダッシュ": false,
        "Wii Sports:タイトル": false,
        "Wii Sports シリーズメドレー": false,
        "Wii Sports Resort:タイトル": false,
        "Wii Sports Resort": false,
        "Wii Sports Resort Ver.2": false,
        "Wii Sports Club:タイトル": false,
        "テニス・トレーニング": false,
        "ベースボール・トレーニング": false,
        "エキサイト トラック": false,
        "襲撃(ソーマブリンガー)": false,
        "ヘラクレスの栄光〜魂の証明〜": false,
        "PERFORMANCE": false,
        "ブルーバーズ": false,
        "さる時計": false,
        "フルーツバスケット": false,
        "あさっての情": false,
        "島の昼": false,
        "島の昼[for]": false,
        "スワンレッスンBGM": false,
        "ドラゴンの戦い": false,
        "すれちがい伝説/すれちがい伝説Ⅱメドレー": false,
        "世界を救え!勇者よ!": false,
        "やみの王": false,
        "希望を胸に": false,
        "いきものづくり クリエイトーイ メドレー": false,
        "ボス1(ひらり 桜侍)": false,
        "ザ・ローリング・ウエスタン 最後の用心棒": false,
        "開拓地の戦い": false,
        "わがままファッション GIRLS MODE よくばり宣言!": false,
        "ファッションショー ポップ": false,
        "Ring Dong Dong!": false,
        "Nintendo Land:タイトルBGM": false,
        "Nintendo Land メドレー": false,
        "ST01 出動! The Wonderful 100!": false,
        "ジャギンガ 天体殲滅機動形態": false,
        "結果発表(Wii Party U)": false,
        "ファミコンリミックス2:タイトル": false,
        "バトル開始(カセキホリダー ムゲンギア)": false,
        "バッジとれ〜るセンター:タイトル": false,
        "バイトウサギのテーマ": false,
        "はじめてのコーナー": false,
        "HOT SPOT_2": false,
        "決戦!ボス": false,
        "決戦!真超魔人": false,
        "ガレージ": false,
        "はちゃめちゃデスク": false,
        "夜明けの砂漠": false,
        "カオスと激闘": false
    }
}
